watchy/__init__.py
watchy/auth.py
watchy/github.py
watchy/paths.py
watchy/storage.py
watchy/cli/__init__.py
watchy/cli/commit.py
watchy/cli/follows.py
watchy/cli/stars.py
watchy-0.0.7.dist-info/METADATA
watchy-0.0.7.dist-info/WHEEL
watchy-0.0.7.dist-info/entry_points.txt
watchy-0.0.7.dist-info/RECORD
