Metadata-Version: 2.4
Name: watchy
Version: 0.0.7
Summary: Fetch and track GitHub stargazers and followers
Project-URL: repository, https://github.com/runsascoded/watchy
Author-email: Ryan Williams <ryan@runsascoded.com>
Classifier: Development Status :: 4 - Beta
Classifier: Intended Audience :: Developers
Classifier: License :: OSI Approved :: MIT License
Classifier: Operating System :: OS Independent
Classifier: Programming Language :: Python :: 3
Classifier: Programming Language :: Python :: 3.9
Classifier: Programming Language :: Python :: 3.10
Classifier: Programming Language :: Python :: 3.11
Classifier: Programming Language :: Python :: 3.12
Requires-Python: >=3.9
Requires-Dist: click
Requires-Dist: gitpython
Requires-Dist: requests
Requires-Dist: utz
Provides-Extra: dev
Requires-Dist: pytest; extra == 'dev'
Requires-Dist: ruff; extra == 'dev'
